huaweicloudsdklts/__init__.py
huaweicloudsdklts/v2/__init__.py
huaweicloudsdklts/v2/lts_async_client.py
huaweicloudsdklts/v2/lts_client.py
huaweicloudsdklts/v2/model/__init__.py
huaweicloudsdklts/v2/model/access_config_base_log_info.py
huaweicloudsdklts/v2/model/access_config_base_log_info_create.py
huaweicloudsdklts/v2/model/access_config_deatil_create.py
huaweicloudsdklts/v2/model/access_config_deatil_update.py
huaweicloudsdklts/v2/model/access_config_format_create.py
huaweicloudsdklts/v2/model/access_config_format_mutil.py
huaweicloudsdklts/v2/model/access_config_format_mutil_create.py
huaweicloudsdklts/v2/model/access_config_format_single.py
huaweicloudsdklts/v2/model/access_config_format_single_create.py
huaweicloudsdklts/v2/model/access_config_format_update.py
huaweicloudsdklts/v2/model/access_config_host_group_id_list.py
huaweicloudsdklts/v2/model/access_config_host_group_id_list_create.py
huaweicloudsdklts/v2/model/access_config_info.py
huaweicloudsdklts/v2/model/access_config_query_log_info.py
huaweicloudsdklts/v2/model/access_config_tag.py
huaweicloudsdklts/v2/model/access_config_time_offset.py
huaweicloudsdklts/v2/model/access_config_time_offset_create.py
huaweicloudsdklts/v2/model/access_config_windows_log_info_create.py
huaweicloudsdklts/v2/model/access_config_windows_log_info_update.py
huaweicloudsdklts/v2/model/annotations.py
huaweicloudsdklts/v2/model/aom_mapping_log_stream_info.py
huaweicloudsdklts/v2/model/aom_mapping_request_info.py
huaweicloudsdklts/v2/model/aom_mapping_rule_info.py
huaweicloudsdklts/v2/model/aom_mapping_rule_resp.py
huaweicloudsdklts/v2/model/aom_mappingfiles_info.py
huaweicloudsdklts/v2/model/brief_struct_template_model.py
huaweicloudsdklts/v2/model/change_alarm_rule_status.py
huaweicloudsdklts/v2/model/chart_config.py
huaweicloudsdklts/v2/model/consumer_checkpoint_info.py
huaweicloudsdklts/v2/model/consumer_group_heart_beat_request.py
huaweicloudsdklts/v2/model/consumer_group_heart_beat_response.py
huaweicloudsdklts-3.1.184.dist-info/METADATA
huaweicloudsdklts-3.1.184.dist-info/WHEEL
huaweicloudsdklts-3.1.184.dist-info/licenses/LICENSE
huaweicloudsdklts-3.1.184.dist-info/RECORD
